[
  {
    "_id": "62d82c8b2da42bcf6501336a",
    "index": 0,
    "guid": "e771f048-0f02-4149-a653-6af88ae42f11",
    "isActive": true,
    "balance": "$2,684.90",
    "picture": "http://placehold.it/32x32",
    "age": 29,
    "eyeColor": "brown",
    "name": "Albert Atkins",
    "gender": "male",
    "company": "KINETICA",
    "email": "albertatkins@kinetica.com",
    "phone": "+1 (878) 498-3566",
    "address": "397 Dupont Street, Oneida, Oregon, 5525",
    "about": "Irure enim dolor cillum excepteur sint duis in sit do enim. Qui irure dolore ex officia proident est nostrud laborum qui. Mollit do cillum eiusmod nisi culpa ut nulla culpa aute cupidatat enim sint elit. Cupidatat et reprehenderit voluptate cillum elit dolor incididunt anim cupidatat adipisicing qui.\r\n",
    "registered": "2020-12-16T09:29:05 -01:00",
    "latitude": -0.956854,
    "longitude": 111.305425,
    "tags": [
      "in",
      "non",
      "nulla",
      "nostrud",
      "duis",
      "nisi",
      "eiusmod"
    ],
    "friends": [
      {
        "id": 0,
        "name": "Latasha Mathis"
      },
      {
        "id": 1,
        "name": "Klein Hicks"
      },
      {
        "id": 2,
        "name": "Adela Levine"
      }
    ],
    "greeting": "Hello, Albert Atkins! You have 3 unread messages.",
    "favoriteFruit": "banana"
  },
  {
    "_id": "62d82c8bfd604cb9bd7a9e00",
    "index": 1,
    "guid": "1b4db944-91c8-4b2d-bf80-740a0ad56af6",
    "isActive": true,
    "balance": "$2,104.21",
    "picture": "http://placehold.it/32x32",
    "age": 24,
    "eyeColor": "blue",
    "name": "Knox Rojas",
    "gender": "male",
    "company": "MATRIXITY",
    "email": "knoxrojas@matrixity.com",
    "phone": "+1 (913) 525-3099",
    "address": "788 Gerritsen Avenue, Mooresburg, District Of Columbia, 5031",
    "about": "Ea in in proident proident reprehenderit fugiat incididunt. Eiusmod ad veniam fugiat nulla ut tempor et. Anim deserunt consectetur aliqua veniam ullamco occaecat culpa velit veniam. Cillum tempor pariatur aliqua consectetur commodo quis duis occaecat cillum est ex. Esse ipsum ipsum pariatur eu.\r\n",
    "registered": "2018-08-21T01:01:30 -02:00",
    "latitude": -45.490677,
    "longitude": -61.468855,
    "tags": [
      "labore",
      "excepteur",
      "fugiat",
      "non",
      "minim",
      "ea",
      "adipisicing"
    ],
    "friends": [
      {
        "id": 0,
        "name": "Blake Valentine"
      },
      {
        "id": 1,
        "name": "Pena Landry"
      },
      {
        "id": 2,
        "name": "Ferguson Bush"
      }
    ],
    "greeting": "Hello, Knox Rojas! You have 4 unread messages.",
    "favoriteFruit": "apple"
  },
  {
    "_id": "62d82c8b8a45da9616bad8f2",
    "index": 2,
    "guid": "0555220a-29e6-4fb6-80de-f7e4c8e7a06c",
    "isActive": false,
    "balance": "$1,422.79",
    "picture": "http://placehold.it/32x32",
    "age": 37,
    "eyeColor": "blue",
    "name": "Pate Clark",
    "gender": "male",
    "company": "FRANSCENE",
    "email": "pateclark@franscene.com",
    "phone": "+1 (953) 481-3964",
    "address": "901 Prescott Place, Eagleville, Northern Mariana Islands, 6711",
    "about": "Laboris pariatur veniam ea ipsum aute aliqua dolor consequat. Eu cupidatat minim laborum culpa id pariatur in. Aliqua est quis duis esse labore labore id. Occaecat non labore dolore velit sit laboris deserunt mollit id. Ipsum ullamco labore voluptate pariatur dolore laboris.\r\n",
    "registered": "2016-02-21T06:46:56 -01:00",
    "latitude": -26.217938,
    "longitude": 138.377136,
    "tags": [
      "nisi",
      "quis",
      "laborum",
      "nulla",
      "incididunt",
      "duis",
      "ad"
    ],
    "friends": [
      {
        "id": 0,
        "name": "Erika Valdez"
      },
      {
        "id": 1,
        "name": "Esther Goodwin"
      },
      {
        "id": 2,
        "name": "Barton Burke"
      }
    ],
    "greeting": "Hello, Pate Clark! You have 6 unread messages.",
    "favoriteFruit": "banana"
  },
  {
    "_id": "62d82c8bcc6c70722b5bc83f",
    "index": 3,
    "guid": "d16e8196-5092-411b-aa11-c562770289ed",
    "isActive": true,
    "balance": "$2,901.32",
    "picture": "http://placehold.it/32x32",
    "age": 27,
    "eyeColor": "green",
    "name": "Jenkins Blackwell",
    "gender": "male",
    "company": "THREDZ",
    "email": "jenkinsblackwell@thredz.com",
    "phone": "+1 (958) 448-3482",
    "address": "187 Buffalo Avenue, Boykin, Montana, 2052",
    "about": "Ea deserunt duis ex nostrud fugiat exercitation voluptate anim sunt ea elit sit. Eiusmod tempor aute excepteur aliqua enim nisi enim aute mollit. Culpa incididunt eiusmod sit minim. Deserunt minim sint Lorem irure commodo elit. Id est excepteur laborum laborum ea commodo anim incididunt Lorem deserunt amet enim nisi reprehenderit. Adipisicing velit nisi incididunt dolore ea nulla est esse cupidatat quis. Occaecat adipisicing tempor voluptate elit commodo reprehenderit tempor.\r\n",
    "registered": "2017-09-26T08:49:58 -02:00",
    "latitude": 29.983581,
    "longitude": 47.611372,
    "tags": [
      "tempor",
      "tempor",
      "exercitation",
      "labore",
      "aliquip",
      "ullamco",
      "ut"
    ],
    "friends": [
      {
        "id": 0,
        "name": "Jillian Swanson"
      },
      {
        "id": 1,
        "name": "York Black"
      },
      {
        "id": 2,
        "name": "Conway Zamora"
      }
    ],
    "greeting": "Hello, Jenkins Blackwell! You have 3 unread messages.",
    "favoriteFruit": "apple"
  },
  {
    "_id": "62d82c8b2849d868a9f1d6e8",
    "index": 4,
    "guid": "0012c65f-a849-4e31-b31d-0b1f682c3fd5",
    "isActive": true,
    "balance": "$1,226.48",
    "picture": "http://placehold.it/32x32",
    "age": 40,
    "eyeColor": "green",
    "name": "Jeanette Bright",
    "gender": "female",
    "company": "EZENTIA",
    "email": "jeanettebright@ezentia.com",
    "phone": "+1 (864) 576-3076",
    "address": "926 Tehama Street, Stevens, Kansas, 7686",
    "about": "Duis nisi ipsum amet laborum aliqua quis in. Excepteur reprehenderit cillum non sunt cupidatat ut cupidatat irure. Duis aliquip minim excepteur qui ea eiusmod et proident minim reprehenderit et.\r\n",
    "registered": "2022-07-04T03:48:50 -02:00",
    "latitude": -31.552139,
    "longitude": -2.904734,
    "tags": [
      "magna",
      "consectetur",
      "occaecat",
      "ea",
      "voluptate",
      "exercitation",
      "quis"
    ],
    "friends": [
      {
        "id": 0,
        "name": "Penny Roberson"
      },
      {
        "id": 1,
        "name": "Velma Lindsey"
      },
      {
        "id": 2,
        "name": "Leah Walker"
      }
    ],
    "greeting": "Hello, Jeanette Bright! You have 3 unread messages.",
    "favoriteFruit": "apple"
  },
  {
    "_id": "62d82c8b5e6854c854b6c031",
    "index": 5,
    "guid": "942ae1c1-3136-4cec-8e35-df953e84535b",
    "isActive": true,
    "balance": "$3,061.95",
    "picture": "http://placehold.it/32x32",
    "age": 38,
    "eyeColor": "blue",
    "name": "Miller Tate",
    "gender": "male",
    "company": "NEOCENT",
    "email": "millertate@neocent.com",
    "phone": "+1 (816) 496-2215",
    "address": "822 Gerry Street, Bannock, Illinois, 2668",
    "about": "Enim culpa dolor sunt mollit ea commodo ullamco dolore aliquip minim aute in velit ullamco. Exercitation nulla labore aliquip ad reprehenderit excepteur velit aute eiusmod cupidatat tempor laborum dolor. Exercitation velit elit ex nisi esse aute exercitation nulla cillum enim laboris voluptate exercitation Lorem.\r\n",
    "registered": "2019-10-20T12:20:24 -02:00",
    "latitude": 81.719401,
    "longitude": 171.363915,
    "tags": [
      "in",
      "deserunt",
      "deserunt",
      "sunt",
      "enim",
      "eiusmod",
      "non"
    ],
    "friends": [
      {
        "id": 0,
        "name": "Ward Moore"
      },
      {
        "id": 1,
        "name": "Spence Williams"
      },
      {
        "id": 2,
        "name": "Carr Burch"
      }
    ],
    "greeting": "Hello, Miller Tate! You have 3 unread messages.",
    "favoriteFruit": "banana"
  }
]
